Metadata-Version: 2.1
Name: tfrecord-tj
Version: 0.0.3
Summary: TFRecord reader
Home-page: https://github.com/seamanj/tfrecord_tj.git
Author: Tao Jiang
Author-email: tjiang.work@gmail.com
License: MIT
Platform: UNKNOWN
